fhir2dataset/__init__.py
fhir2dataset/api_caller.py
fhir2dataset/data_class.py
fhir2dataset/fhirpath.py
fhir2dataset/fhirrules_getter.py
fhir2dataset/graph_tools.py
fhir2dataset/graphquery.py
fhir2dataset/parser.py
fhir2dataset/query.py
fhir2dataset/timer.py
fhir2dataset/url_builder.py
fhir2dataset/visualization_tools.py
fhir2dataset/metadata/.gitignore
fhir2dataset/metadata/SearchParameters.json
fhir2dataset/metadata/package-lock.json
fhir2dataset/metadata/package.json
fhir2dataset/metadata/node_modules/.bin/cake
fhir2dataset/metadata/node_modules/.bin/coffee
fhir2dataset/metadata/node_modules/.bin/esparse
fhir2dataset/metadata/node_modules/.bin/esvalidate
fhir2dataset/metadata/node_modules/.bin/fhirpath
fhir2dataset/metadata/node_modules/.bin/js-yaml
fhir2dataset/metadata/node_modules/@lhncbc/ucum-lhc/CHANGELOG.md
fhir2dataset/metadata/node_modules/@lhncbc/ucum-lhc/LICENSE.md
fhir2dataset/metadata/node_modules/@lhncbc/ucum-lhc/README.md
fhir2dataset/metadata/node_modules/@lhncbc/ucum-lhc/package.json
fhir2dataset/metadata/node_modules/@lhncbc/ucum-lhc/browser-dist/ucum-lhc.js
fhir2dataset/metadata/node_modules/@lhncbc/ucum-lhc/data/ucumDefs.min.json
fhir2dataset/metadata/node_modules/@lhncbc/ucum-lhc/source/config.js
fhir2dataset/metadata/node_modules/@lhncbc/ucum-lhc/source/dimension.js
fhir2dataset/metadata/node_modules/@lhncbc/ucum-lhc/source/jsonArrayPack.js
fhir2dataset/metadata/node_modules/@lhncbc/ucum-lhc/source/prefix.js
fhir2dataset/metadata/node_modules/@lhncbc/ucum-lhc/source/prefixTables.js
fhir2dataset/metadata/node_modules/@lhncbc/ucum-lhc/source/ucumFunctions.js
fhir2dataset/metadata/node_modules/@lhncbc/ucum-lhc/source/ucumInternalUtils.js
fhir2dataset/metadata/node_modules/@lhncbc/ucum-lhc/source/ucumJsonDefs.js
fhir2dataset/metadata/node_modules/@lhncbc/ucum-lhc/source/ucumLhcUtils.js
fhir2dataset/metadata/node_modules/@lhncbc/ucum-lhc/source/ucumPkg.js
fhir2dataset/metadata/node_modules/@lhncbc/ucum-lhc/source/ucumXmlDocument.js
fhir2dataset-0.1.2.dist-info/LICENSE
fhir2dataset-0.1.2.dist-info/METADATA
fhir2dataset-0.1.2.dist-info/WHEEL
fhir2dataset-0.1.2.dist-info/top_level.txt
fhir2dataset-0.1.2.dist-info/RECORD
