Metadata-Version: 2.1
Name: fhir2dataset
Version: 0.1.2
Summary: Transform FHIR to Dataset
Home-page: https://github.com/arkhn/FHIR2Dataset
Author: Lucile Saulnier
Author-email: contact@arkhn.com
License: Apache License 2.0
Keywords: arkhn,medical,fhir,FHIR,Dataset,API
Platform: UNKNOWN
Classifier: Development Status :: 3 - Alpha
Classifier: Intended Audience :: Developers
Classifier: Topic :: Software Development :: Build Tools
Classifier: Programming Language :: Python :: 3.7
Classifier: Programming Language :: Python :: 3.8
Requires-Dist: pandas (==1.0.3)
Requires-Dist: matplotlib (==3.1.3)
Requires-Dist: networkx (==2.4)
Requires-Dist: requests (==2.23.0)
Requires-Dist: dacite (==1.5.1)
